hamming_check/__init__.py
hamming_check/__version__.py
hamming_check/entry_points.py
hamming_check/cli/__init__.py
hamming_check/cli/__version__.py
hamming_check/cli/cli.py
hamming_check/hamming/__init__.py
hamming_check/hamming/__version__.py
hamming_check/hamming/decode_result.py
hamming_check/hamming/decode_status.py
hamming_check/hamming/hamming.py
hamming_check/io/__init__.py
hamming_check/io/__version__.py
hamming_check/io/_bytes_bit_iterator.py
hamming_check/io/_file_byte_iterator.py
hamming_check/io/bytes.py
hamming_check/io/file.py
hamming_check/types/__init__.py
hamming_check/types/__version__.py
hamming_check/types/verbosity_types.py
hamming_check/utils/__init__.py
hamming_check/utils/__version__.py
hamming_check/utils/utils.py
hamming_check-1.0.2.dist-info/LICENSE
hamming_check-1.0.2.dist-info/METADATA
hamming_check-1.0.2.dist-info/WHEEL
hamming_check-1.0.2.dist-info/entry_points.txt
hamming_check-1.0.2.dist-info/top_level.txt
hamming_check-1.0.2.dist-info/RECORD
