Metadata-Version: 2.1
Name: hamming-check
Version: 1.0.2
Summary: hamming-check: File integrity checker
Home-page: https://github.com/tomcat-42/hamming-check
Author: Pablo Alessandro Santos Hugen
Author-email: PabloASHugen@protonmail.com
License: Apache 2.0
Keywords: hamming code sec dec
Platform: UNKNOWN
Classifier: Development Status :: 4 - Beta
Classifier: Intended Audience :: Developers
Classifier: Programming Language :: Python :: 3.10
Requires-Python: >=3.7.*
License-File: LICENSE
Requires-Dist: bitarray
